pnu_strfile-1.0.3.data/data/man/man8/strfile.8.gz
pnu_strfile-1.0.3.data/data/man/man8/unstr.8.gz
strfile/__init__.py
strfile/main.py
pnu_strfile-1.0.3.dist-info/License
pnu_strfile-1.0.3.dist-info/METADATA
pnu_strfile-1.0.3.dist-info/WHEEL
pnu_strfile-1.0.3.dist-info/entry_points.txt
pnu_strfile-1.0.3.dist-info/top_level.txt
pnu_strfile-1.0.3.dist-info/RECORD
